symbiosil/__init__.py
symbiosil/cli.py
symbiosil/commons/__init__.py
symbiosil/commons/logging.py
symbiosil/core/__init__.py
symbiosil/core/action.py
symbiosil/core/sense.py
symbiosil-1.0.0.dist-info/LICENSE
symbiosil-1.0.0.dist-info/METADATA
symbiosil-1.0.0.dist-info/WHEEL
symbiosil-1.0.0.dist-info/entry_points.txt
symbiosil-1.0.0.dist-info/top_level.txt
symbiosil-1.0.0.dist-info/RECORD
