Metadata-Version: 2.1
Name: symbiosil
Version: 1.0.0
Summary: Symbiosil is living AI bot framework.
Home-page: https://github.com/stacknix/symbiosil
Author: Ashish Sahu
Author-email: spiraldeveloper@gmail.com
License: MIT
Keywords: python package symbiosil
Platform: UNKNOWN
Classifier: Programming Language :: Python :: 3
Classifier: License :: OSI Approved :: MIT License
Classifier: Operating System :: OS Independent
License-File: LICENSE
Requires-Dist: requests (==2.28.1)
Requires-Dist: redis (==4.3.4)
Requires-Dist: click (==8.1.3)
